[
  {
    "_id": {
      "$oid": "67567046f5491e6d0d74d6f7"
    },
    "CustomerPhone": "0865665985",
    "OrderDate": {
      "$date": "2024-12-09T04:21:26.415Z"
    },
    "payment": "Paid",
    "ShipperID": 3,
    "TotalAmount": 139.98000000000002,
    "OrderDetails": [
      {
        "ProductID": 9,
        "Quantity": 1
      },
      {
        "ProductID": 10,
        "Quantity": 1
      }
    ]
  },
  {
    "_id": {
      "$oid": "6756763ebbf0ff0ae1a20dbc"
    },
    "CustomerPhone": "0865665985",
    "OrderDate": {
      "$date": "2024-12-09T04:46:54.652Z"
    },
    "payment": "Paid",
    "ShipperID": 3,
    "TotalAmount": 399.97,
    "OrderDetails": [
      {
        "ProductID": 7,
        "Quantity": 1
      },
      {
        "ProductID": 8,
        "Quantity": 2
      }
    ]
  },
  {
    "_id": {
      "$oid": "6756790095c0a7512c920b22"
    },
    "CustomerPhone": "0865665985",
    "OrderDate": {
      "$date": "2024-12-09T04:58:40.689Z"
    },
    "payment": "Paid",
    "ShipperID": 2,
    "TotalAmount": 239.94,
    "OrderDetails": [
      {
        "ProductID": 6,
        "Quantity": 6
      }
    ]
  },
  {
    "_id": {
      "$oid": "6757f549dcf8af4630311dce"
    },
    "CustomerPhone": "0865665985",
    "OrderDate": {
      "$date": "2024-12-10T08:01:13.224Z"
    },
    "payment": "Paid",
    "ShipperID": 2,
    "TotalAmount": 929.93,
    "OrderDetails": [
      {
        "ProductID": 1,
        "Quantity": 1
      },
      {
        "ProductID": 4,
        "Quantity": 1
      },
      {
        "ProductID": 5,
        "Quantity": 1
      },
      {
        "ProductID": 9,
        "Quantity": 4
      }
    ]
  },
  {
    "_id": {
      "$oid": "675854c59bc73360ddac3594"
    },
    "CustomerPhone": "0865665985",
    "OrderDate": {
      "$date": "2024-12-10T14:48:37.413Z"
    },
    "payment": "Paid",
    "ShipperID": 3,
    "TotalAmount": 349.98,
    "OrderDetails": [
      {
        "ProductID": 1,
        "Quantity": 1
      },
      {
        "ProductID": 2,
        "Quantity": 1
      }
    ]
  },
  {
    "_id": {
      "$oid": "675854fa2e1d20759ce02dc5"
    },
    "CustomerPhone": "0865665985",
    "OrderDate": {
      "$date": "2024-12-10T14:49:30.383Z"
    },
    "payment": "Paid",
    "ShipperID": 3,
    "TotalAmount": 9.99,
    "OrderDetails": [
      {
        "ProductID": 10,
        "Quantity": 1
      }
    ]
  },
  {
    "_id": {
      "$oid": "675867d004e47f3e7ff44d29"
    },
    "CustomerPhone": "0865665985",
    "OrderDate": {
      "$date": "2024-12-10T16:09:52.854Z"
    },
    "payment": "Paid",
    "ShipperID": 3,
    "TotalAmount": 1499.9,
    "OrderDetails": [
      {
        "ProductID": 8,
        "Quantity": 10
      }
    ]
  },
  {
    "_id": {
      "$oid": "6758681b976ec0081c49bae5"
    },
    "CustomerPhone": "0865665985",
    "OrderDate": {
      "$date": "2024-12-10T16:11:07.893Z"
    },
    "payment": "Paid",
    "ShipperID": 2,
    "TotalAmount": 369.94,
    "OrderDetails": [
      {
        "ProductID": 2,
        "Quantity": 1
      },
      {
        "ProductID": 4,
        "Quantity": 1
      },
      {
        "ProductID": 6,
        "Quantity": 2
      },
      {
        "ProductID": 8,
        "Quantity": 1
      },
      {
        "ProductID": 10,
        "Quantity": 1
      }
    ]
  },
  {
    "_id": {
      "$oid": "67586826976ec0081c49bae6"
    },
    "CustomerPhone": "0865665985",
    "OrderDate": {
      "$date": "2024-12-10T16:11:18.727Z"
    },
    "payment": "Paid",
    "ShipperID": 3,
    "TotalAmount": 179.96,
    "OrderDetails": [
      {
        "ProductID": 2,
        "Quantity": 1
      },
      {
        "ProductID": 3,
        "Quantity": 1
      },
      {
        "ProductID": 4,
        "Quantity": 1
      },
      {
        "ProductID": 5,
        "Quantity": 1
      }
    ]
  },
  {
    "_id": {
      "$oid": "67586830976ec0081c49bae7"
    },
    "CustomerPhone": "0865665985",
    "OrderDate": {
      "$date": "2024-12-10T16:11:28.826Z"
    },
    "payment": "Paid",
    "ShipperID": 2,
    "TotalAmount": 399.95,
    "OrderDetails": [
      {
        "ProductID": 7,
        "Quantity": 1
      },
      {
        "ProductID": 8,
        "Quantity": 1
      },
      {
        "ProductID": 9,
        "Quantity": 1
      },
      {
        "ProductID": 10,
        "Quantity": 2
      }
    ]
  },
  {
    "_id": {
      "$oid": "67586be3ab09852beacdd0d8"
    },
    "CustomerPhone": "0865665985",
    "OrderDate": {
      "$date": "2024-12-10T16:27:15.281Z"
    },
    "payment": "Paid",
    "ShipperID": 2,
    "TotalAmount": 149.99,
    "OrderDetails": [
      {
        "ProductID": 8,
        "Quantity": 1
      }
    ]
  },
  {
    "_id": {
      "$oid": "67586be8ab09852beacdd0d9"
    },
    "CustomerPhone": "0865665985",
    "OrderDate": {
      "$date": "2024-12-10T16:27:20.066Z"
    },
    "payment": "Paid",
    "ShipperID": 2,
    "TotalAmount": 129.99,
    "OrderDetails": [
      {
        "ProductID": 9,
        "Quantity": 1
      }
    ]
  },
  {
    "_id": {
      "$oid": "67586becab09852beacdd0da"
    },
    "CustomerPhone": "0865665985",
    "OrderDate": {
      "$date": "2024-12-10T16:27:24.744Z"
    },
    "payment": "Paid",
    "ShipperID": 2,
    "TotalAmount": 19.99,
    "OrderDetails": [
      {
        "ProductID": 3,
        "Quantity": 1
      }
    ]
  },
  {
    "_id": {
      "$oid": "6758ebe53c5760682ddeaa43"
    },
    "CustomerPhone": "0865665985",
    "OrderDate": {
      "$date": "2024-12-11T01:33:25.712Z"
    },
    "payment": "Paid",
    "ShipperID": 2,
    "TotalAmount": 319.95,
    "OrderDetails": [
      {
        "ProductID": 5,
        "Quantity": 3
      },
      {
        "ProductID": 7,
        "Quantity": 1
      },
      {
        "ProductID": 9,
        "Quantity": 1
      }
    ]
  },
  {
    "_id": {
      "$oid": "6758ebeb3c5760682ddeaa44"
    },
    "CustomerPhone": "0865665985",
    "OrderDate": {
      "$date": "2024-12-11T01:33:31.911Z"
    },
    "payment": "Paid",
    "ShipperID": 2,
    "TotalAmount": 149.97,
    "OrderDetails": [
      {
        "ProductID": 4,
        "Quantity": 1
      },
      {
        "ProductID": 5,
        "Quantity": 1
      },
      {
        "ProductID": 6,
        "Quantity": 1
      }
    ]
  },
  {
    "_id": {
      "$oid": "675a5c0ae1512a14c7436b73"
    },
    "CustomerPhone": "123456789",
    "OrderDate": {
      "$date": "2024-12-12T03:44:10.923Z"
    },
    "payment": "Paid",
    "ShipperID": 2,
    "TotalAmount": 379.97,
    "OrderDetails": [
      {
        "ProductID": 1,
        "Quantity": 1
      },
      {
        "ProductID": 2,
        "Quantity": 1
      },
      {
        "ProductID": 5,
        "Quantity": 1
      }
    ]
  },
  {
    "_id": {
      "$oid": "675a5c1de1512a14c7436b74"
    },
    "CustomerPhone": "123456789",
    "OrderDate": {
      "$date": "2024-12-12T03:44:29.281Z"
    },
    "payment": "Paid",
    "ShipperID": 2,
    "TotalAmount": 699.91,
    "OrderDetails": [
      {
        "ProductID": 1,
        "Quantity": 2
      },
      {
        "ProductID": 3,
        "Quantity": 1
      },
      {
        "ProductID": 5,
        "Quantity": 1
      },
      {
        "ProductID": 10,
        "Quantity": 5
      }
    ]
  }
]
